{
  "AUTH0_DOMAIN": "sf-futuresengine-prod.us.auth0.com",
  "AUTH0_CLIENT_ID": "RWu0rO01uFKzQD5cWpMARTBwZOROqboL",
  "AUTH0_ALLOW_DELETE": false,
  "AUTH0_EXCLUDED": ["customDomains"],
  "AUTH0_PRESERVE_KEYWORDS": true,
  "AUTH0_KEYWORD_REPLACE_MAPPINGS": {
    "ENV": "prod",
    "CUSTOM_DOMAIN": "login.futuresengine.com",
    "CUSTOM_DOMAIN_CNAME": "sf-futuresengine-prod-cd-qcv5xfnoybi5wajv.edge.tenants.us.auth0.com",
    "SUPPORT_EMAIL": "support@futuresengine.com",
    "AUTH0_DOMAIN": "sf-futuresengine-prod.us.auth0.com",
    "ALLOWED_WEB_ORIGINS": ["https://www.tekalo.org", "https://*.common-app-frontend.pages.dev"],
    "TEKALO_CLIENT_CALLBACKS": ["https://www.tekalo.org", "https://*.common-app-frontend.pages.dev"],
    "ALLOWED_LOGOUT_URLS": ["https://www.tekalo.org", "https://*.common-app-frontend.pages.dev"],
    "DEFAULT_FROM_ADDRESS": "support@futuresengine.com"
  }
}
